<?xml version="1.0" encoding="UTF-8"?>
<!DOCTYPE list SYSTEM "item.dtd">
<list>
	<etcitem id="96200" name="Package: +4 Talisman of Authority (Time-limited)" add_name="Sealed">
		<set name="icon" value="icon.sayhas_talisman_new"/>
		<set name="stackable" value="true"/>
		<set name="crystal_type" value="NONE"/>
		<set name="tradeable" value="false"/>
		<set name="dropable" value="false"/>
		<set name="privatestoreable" value="false"/>
		<set name="sellable" value="false"/>
		<set name="clan_warehouseable" value="false"/>
		<set name="freightable" value="true"/>
		<set name="type" value="EXTRACTABLE"/>
		<capsuled_items>
			<capsuled_item id="91061" min_count="1" max_count="1" chance="100" enchant="4"/><!--Talisman of Authority-->
		</capsuled_items>
	</etcitem>
	<etcitem id="96201" name="Package: Einhasad's Pendant Lv. 2 (Time-limited)" add_name="Sealed">
		<set name="icon" value="BranchIcon.Icon.bm_pendant_pve_white"/>
		<set name="stackable" value="true"/>
		<set name="crystal_type" value="NONE"/>
		<set name="tradeable" value="false"/>
		<set name="dropable" value="false"/>
		<set name="privatestoreable" value="false"/>
		<set name="sellable" value="false"/>
		<set name="clan_warehouseable" value="false"/>
		<set name="freightable" value="true"/>
		<set name="type" value="EXTRACTABLE"/>
		<capsuled_items>
			<capsuled_item id="93297" min_count="1" max_count="1" chance="100"/><!--Einhasad’s Pendant Lv. 2-->
		</capsuled_items>
	</etcitem>
	<etcitem id="96202" name="Package: +4 Circlet of Hero (Time-limited)" add_name="Sealed">
		<set name="icon" value="icon.accessory_barka_karm_i00"/>
		<set name="stackable" value="true"/>
		<set name="crystal_type" value="NONE"/>
		<set name="tradeable" value="false"/>
		<set name="dropable" value="false"/>
		<set name="privatestoreable" value="false"/>
		<set name="sellable" value="false"/>
		<set name="clan_warehouseable" value="false"/>
		<set name="freightable" value="true"/>
		<set name="type" value="EXTRACTABLE"/>
		<capsuled_items>
			<capsuled_item id="94166" min_count="1" max_count="1" chance="100" enchant="4"/><!--Circlet of Hero-->
		</capsuled_items>
	</etcitem>
	<etcitem id="96203" name="Package: +6 Talisman of Eva (Time-limited)" add_name="Sealed">
		<set name="icon" value="icon.bm_eva_talisman"/>
		<set name="stackable" value="true"/>
		<set name="crystal_type" value="NONE"/>
		<set name="tradeable" value="false"/>
		<set name="dropable" value="false"/>
		<set name="privatestoreable" value="false"/>
		<set name="sellable" value="false"/>
		<set name="clan_warehouseable" value="false"/>
		<set name="freightable" value="true"/>
		<set name="type" value="EXTRACTABLE"/>
		<capsuled_items>
			<capsuled_item id="92018" min_count="1" max_count="1" chance="100" enchant="6"/><!--Talisman of Eva-->
		</capsuled_items>
	</etcitem>
	<etcitem id="96204" name="Package: +6 Dragon Belt (Time-limited)" add_name="Sealed">
		<set name="icon" value="icon.r2_belt_i01"/>
		<set name="stackable" value="true"/>
		<set name="crystal_type" value="NONE"/>
		<set name="tradeable" value="false"/>
		<set name="dropable" value="false"/>
		<set name="privatestoreable" value="false"/>
		<set name="sellable" value="false"/>
		<set name="clan_warehouseable" value="false"/>
		<set name="freightable" value="true"/>
		<set name="type" value="EXTRACTABLE"/>
		<capsuled_items>
			<capsuled_item id="91862" min_count="1" max_count="1" chance="100" enchant="6"/><!--Dragon Belt-->
		</capsuled_items>
	</etcitem>
	<etcitem id="96205" name="Package: +6 Talisman of Authority (Time-limited)" add_name="Sealed">
		<set name="icon" value="icon.sayhas_talisman_new"/>
		<set name="stackable" value="true"/>
		<set name="crystal_type" value="NONE"/>
		<set name="tradeable" value="false"/>
		<set name="dropable" value="false"/>
		<set name="privatestoreable" value="false"/>
		<set name="sellable" value="false"/>
		<set name="clan_warehouseable" value="false"/>
		<set name="freightable" value="true"/>
		<set name="type" value="EXTRACTABLE"/>
		<capsuled_items>
			<capsuled_item id="91061" min_count="1" max_count="1" chance="100" enchant="6"/><!--Talisman of Authority-->
		</capsuled_items>
	</etcitem>
	<etcitem id="96206" name="Package: +6 Circlet of Hero (Time-limited)" add_name="Sealed">
		<set name="icon" value="icon.accessory_barka_karm_i00"/>
		<set name="stackable" value="true"/>
		<set name="crystal_type" value="NONE"/>
		<set name="tradeable" value="false"/>
		<set name="dropable" value="false"/>
		<set name="privatestoreable" value="false"/>
		<set name="sellable" value="false"/>
		<set name="clan_warehouseable" value="false"/>
		<set name="freightable" value="true"/>
		<set name="type" value="EXTRACTABLE"/>
		<capsuled_items>
			<capsuled_item id="94166" min_count="1" max_count="1" chance="100" enchant="6"/><!--Circlet of Hero-->
		</capsuled_items>
	</etcitem>
	<etcitem id="96207" name="Package: Brooch Lv. 5 (Time-limited)" add_name="Sealed">
		<set name="icon" value="icon.etc_bm_brooch_lavianrose_i06"/>
		<set name="stackable" value="true"/>
		<set name="crystal_type" value="NONE"/>
		<set name="tradeable" value="false"/>
		<set name="dropable" value="false"/>
		<set name="privatestoreable" value="false"/>
		<set name="sellable" value="false"/>
		<set name="clan_warehouseable" value="false"/>
		<set name="freightable" value="true"/>
		<set name="type" value="EXTRACTABLE"/>
		<capsuled_items>
			<capsuled_item id="91304" min_count="1" max_count="1" chance="100"/><!--Brooch Lv. 5-->
		</capsuled_items>
	</etcitem>
	<etcitem id="96208" name="Package: Opal Lv. 4 (Time-limited)" add_name="Sealed">
		<set name="icon" value="icon.etc_bm_jewel_opal_i00"/>
		<set name="stackable" value="true"/>
		<set name="crystal_type" value="NONE"/>
		<set name="tradeable" value="false"/>
		<set name="dropable" value="false"/>
		<set name="privatestoreable" value="false"/>
		<set name="sellable" value="false"/>
		<set name="clan_warehouseable" value="false"/>
		<set name="freightable" value="true"/>
		<set name="type" value="EXTRACTABLE"/>
		<capsuled_items>
			<capsuled_item id="92049" min_count="1" max_count="1" chance="100"/><!--Opal Lv. 4-->
		</capsuled_items>
	</etcitem>
	<etcitem id="96209" name="Package: Coral Lv. 4 (Time-limited)" add_name="Sealed">
		<set name="icon" value="icon.etc_bm_jewel_coral_i00"/>
		<set name="stackable" value="true"/>
		<set name="crystal_type" value="NONE"/>
		<set name="tradeable" value="false"/>
		<set name="dropable" value="false"/>
		<set name="privatestoreable" value="false"/>
		<set name="sellable" value="false"/>
		<set name="clan_warehouseable" value="false"/>
		<set name="freightable" value="true"/>
		<set name="type" value="EXTRACTABLE"/>
		<capsuled_items>
			<capsuled_item id="92059" min_count="1" max_count="1" chance="100"/><!--Coral Lv. 4-->
		</capsuled_items>
	</etcitem>
	<etcitem id="96210" name="Package: Onyx Lv. 4 (Time-limited)" add_name="Sealed">
		<set name="icon" value="icon.etc_bm_jewel_onyx_i00"/>
		<set name="stackable" value="true"/>
		<set name="crystal_type" value="NONE"/>
		<set name="tradeable" value="false"/>
		<set name="dropable" value="false"/>
		<set name="privatestoreable" value="false"/>
		<set name="sellable" value="false"/>
		<set name="clan_warehouseable" value="false"/>
		<set name="freightable" value="true"/>
		<set name="type" value="EXTRACTABLE"/>
		<capsuled_items>
			<capsuled_item id="92069" min_count="1" max_count="1" chance="100"/><!--Onyx Lv. 4-->
		</capsuled_items>
	</etcitem>
	<etcitem id="96211" name="Package: Spinel Lv. 4 (Time-limited)" add_name="Sealed">
		<set name="icon" value="icon.etc_bm_jewel_garnet_i00"/>
		<set name="stackable" value="true"/>
		<set name="crystal_type" value="NONE"/>
		<set name="tradeable" value="false"/>
		<set name="dropable" value="false"/>
		<set name="privatestoreable" value="false"/>
		<set name="sellable" value="false"/>
		<set name="clan_warehouseable" value="false"/>
		<set name="freightable" value="true"/>
		<set name="type" value="EXTRACTABLE"/>
		<capsuled_items>
			<capsuled_item id="92079" min_count="1" max_count="1" chance="100"/><!--Spinel Lv. 4-->
		</capsuled_items>
	</etcitem>
	<etcitem id="96212" name="Package: Zircon Lv. 4 (Time-limited)" add_name="Sealed">
		<set name="icon" value="icon.etc_bm_jewel_bloodstone_i00"/>
		<set name="stackable" value="true"/>
		<set name="crystal_type" value="NONE"/>
		<set name="tradeable" value="false"/>
		<set name="dropable" value="false"/>
		<set name="privatestoreable" value="false"/>
		<set name="sellable" value="false"/>
		<set name="clan_warehouseable" value="false"/>
		<set name="freightable" value="true"/>
		<set name="type" value="EXTRACTABLE"/>
		<capsuled_items>
			<capsuled_item id="92089" min_count="1" max_count="1" chance="100"/><!--Zircon Lv. 4-->
		</capsuled_items>
	</etcitem>
	<etcitem id="96213" name="Package: Moonstone Lv. 4 (Time-limited)" add_name="Sealed">
		<set name="icon" value="icon.etc_bm_jewel_moonstone_i00"/>
		<set name="stackable" value="true"/>
		<set name="crystal_type" value="NONE"/>
		<set name="tradeable" value="false"/>
		<set name="dropable" value="false"/>
		<set name="privatestoreable" value="false"/>
		<set name="sellable" value="false"/>
		<set name="clan_warehouseable" value="false"/>
		<set name="freightable" value="true"/>
		<set name="type" value="EXTRACTABLE"/>
		<capsuled_items>
			<capsuled_item id="92099" min_count="1" max_count="1" chance="100"/><!--Moonstone Lv. 4-->
		</capsuled_items>
	</etcitem>
	<etcitem id="96214" name="Package: Agathion Lv. 5 (Time-limited)" add_name="Sealed">
		<set name="icon" value="icon.pi_high_agathion_bracelet_i00"/>
		<set name="stackable" value="true"/>
		<set name="crystal_type" value="NONE"/>
		<set name="tradeable" value="false"/>
		<set name="dropable" value="false"/>
		<set name="privatestoreable" value="false"/>
		<set name="sellable" value="false"/>
		<set name="clan_warehouseable" value="false"/>
		<set name="freightable" value="true"/>
		<set name="type" value="EXTRACTABLE"/>
		<capsuled_items>
			<capsuled_item id="91161" min_count="1" max_count="1" chance="100"/><!--Agathion Bracelet Lv. 5-->
		</capsuled_items>
	</etcitem>
	<etcitem id="96215" name="Package: +5 Agathion Ignis (Time-limited)" add_name="Sealed">
		<set name="icon" value="icon.agathion_fire_1"/>
		<set name="stackable" value="true"/>
		<set name="crystal_type" value="NONE"/>
		<set name="tradeable" value="false"/>
		<set name="dropable" value="false"/>
		<set name="privatestoreable" value="false"/>
		<set name="sellable" value="false"/>
		<set name="clan_warehouseable" value="false"/>
		<set name="freightable" value="true"/>
		<set name="type" value="EXTRACTABLE"/>
		<capsuled_items>
			<capsuled_item id="93128" min_count="1" max_count="1" chance="100" enchant="5"/><!--Agathion Ignis-->
		</capsuled_items>
	</etcitem>
	<etcitem id="96216" name="Package: +5 Agathion Nebula (Time-limited)" add_name="Sealed">
		<set name="icon" value="icon.agathion_water_1"/>
		<set name="stackable" value="true"/>
		<set name="crystal_type" value="NONE"/>
		<set name="tradeable" value="false"/>
		<set name="dropable" value="false"/>
		<set name="privatestoreable" value="false"/>
		<set name="sellable" value="false"/>
		<set name="clan_warehouseable" value="false"/>
		<set name="freightable" value="true"/>
		<set name="type" value="EXTRACTABLE"/>
		<capsuled_items>
			<capsuled_item id="93129" min_count="1" max_count="1" chance="100" enchant="5"/><!--Agathion Nebula-->
		</capsuled_items>
	</etcitem>
	<etcitem id="96217" name="Package: +5 Agathion Procella (Time-limited)" add_name="Sealed">
		<set name="icon" value="icon.agathion_wind_1"/>
		<set name="stackable" value="true"/>
		<set name="crystal_type" value="NONE"/>
		<set name="tradeable" value="false"/>
		<set name="dropable" value="false"/>
		<set name="privatestoreable" value="false"/>
		<set name="sellable" value="false"/>
		<set name="clan_warehouseable" value="false"/>
		<set name="freightable" value="true"/>
		<set name="type" value="EXTRACTABLE"/>
		<capsuled_items>
			<capsuled_item id="93130" min_count="1" max_count="1" chance="100" enchant="5"/><!--Agathion Procella-->
		</capsuled_items>
	</etcitem>
	<etcitem id="96218" name="Package: +5 Agathion Petram (Time-limited)" add_name="Sealed">
		<set name="icon" value="icon.agathion_earth_1"/>
		<set name="stackable" value="true"/>
		<set name="crystal_type" value="NONE"/>
		<set name="tradeable" value="false"/>
		<set name="dropable" value="false"/>
		<set name="privatestoreable" value="false"/>
		<set name="sellable" value="false"/>
		<set name="clan_warehouseable" value="false"/>
		<set name="freightable" value="true"/>
		<set name="type" value="EXTRACTABLE"/>
		<capsuled_items>
			<capsuled_item id="93131" min_count="1" max_count="1" chance="100" enchant="5"/><!--Agathion Petram-->
		</capsuled_items>
	</etcitem>
	<etcitem id="96219" name="Package: +5 Agathion Joy (Time-limited)" add_name="Sealed">
		<set name="icon" value="icon.pleasure_agathion_i00"/>
		<set name="stackable" value="true"/>
		<set name="crystal_type" value="NONE"/>
		<set name="tradeable" value="false"/>
		<set name="dropable" value="false"/>
		<set name="privatestoreable" value="false"/>
		<set name="sellable" value="false"/>
		<set name="clan_warehouseable" value="false"/>
		<set name="freightable" value="true"/>
		<set name="type" value="EXTRACTABLE"/>
		<capsuled_items>
			<capsuled_item id="93132" min_count="1" max_count="1" chance="100" enchant="5"/><!--Agathion Joy-->
		</capsuled_items>
	</etcitem>
	<etcitem id="96220" name="Package: Talisman Bracelet Lv. 5 (Time-limited)" add_name="Sealed">
		<set name="icon" value="icon.dimension_bracelet_i04"/>
		<set name="stackable" value="true"/>
		<set name="crystal_type" value="NONE"/>
		<set name="tradeable" value="false"/>
		<set name="dropable" value="false"/>
		<set name="privatestoreable" value="false"/>
		<set name="sellable" value="false"/>
		<set name="clan_warehouseable" value="false"/>
		<set name="freightable" value="true"/>
		<set name="type" value="EXTRACTABLE"/>
		<capsuled_items>
			<capsuled_item id="92031" min_count="1" max_count="1" chance="100"/><!--Talisman Bracelet Lv. 5-->
		</capsuled_items>
	</etcitem>
	<etcitem id="96221" name="Package: Venir's Talisman Lv. 12 (Time-limited)" add_name="Sealed">
		<set name="icon" value="icon.benir_talisman_i00"/>
		<set name="stackable" value="true"/>
		<set name="crystal_type" value="NONE"/>
		<set name="tradeable" value="false"/>
		<set name="dropable" value="false"/>
		<set name="privatestoreable" value="false"/>
		<set name="sellable" value="false"/>
		<set name="clan_warehouseable" value="false"/>
		<set name="freightable" value="true"/>
		<set name="type" value="EXTRACTABLE"/>
		<capsuled_items>
			<capsuled_item id="91088" min_count="1" max_count="1" chance="100"/><!--Venir's Talisman Lv. 12-->
		</capsuled_items>
	</etcitem>
	<etcitem id="96222" name="Herphah's Equipment Pack Lv. 55 (Time-limited)" add_name="Sealed">
		<set name="icon" value="icon.etc_exchange_box_i00"/>
		<set name="stackable" value="true"/>
		<set name="crystal_type" value="NONE"/>
		<set name="tradeable" value="false"/>
		<set name="dropable" value="false"/>
		<set name="privatestoreable" value="false"/>
		<set name="sellable" value="false"/>
		<set name="clan_warehouseable" value="false"/>
		<set name="freightable" value="true"/>
		<set name="type" value="EXTRACTABLE"/>
		<capsuled_items>
			<capsuled_item id="96197" min_count="1" max_count="1" chance="100"/><!--Package: +4 Talisman of Eva (Time-limited)-->
			<capsuled_item id="96223" min_count="1" max_count="1" chance="100"/><!--Herphah's Equipment Pack Lv. 60 (Time-limited)-->
		</capsuled_items>
	</etcitem>
	<etcitem id="96223" name="Herphah's Equipment Pack Lv. 60 (Time-limited)" add_name="Sealed">
		<set name="icon" value="icon.etc_exchange_box_i00"/>
		<set name="stackable" value="true"/>
		<set name="crystal_type" value="NONE"/>
		<set name="tradeable" value="false"/>
		<set name="dropable" value="false"/>
		<set name="privatestoreable" value="false"/>
		<set name="sellable" value="false"/>
		<set name="clan_warehouseable" value="false"/>
		<set name="freightable" value="true"/>
		<set name="type" value="EXTRACTABLE"/>
		<capsuled_items>
			<capsuled_item id="96198" min_count="1" max_count="1" chance="100"/><!--Package: +4 Dragon Belt (Time-limited)-->
			<capsuled_item id="96224" min_count="1" max_count="1" chance="100"/><!--Herphah's Equipment Pack Lv. 65 (Time-limited)-->
		</capsuled_items>
	</etcitem>
	<etcitem id="96224" name="Herphah's Equipment Pack Lv. 65 (Time-limited)" add_name="Sealed">
		<set name="icon" value="icon.etc_exchange_box_i00"/>
		<set name="stackable" value="true"/>
		<set name="crystal_type" value="NONE"/>
		<set name="tradeable" value="false"/>
		<set name="dropable" value="false"/>
		<set name="privatestoreable" value="false"/>
		<set name="sellable" value="false"/>
		<set name="clan_warehouseable" value="false"/>
		<set name="freightable" value="true"/>
		<set name="type" value="EXTRACTABLE"/>
		<capsuled_items>
			<capsuled_item id="96199" min_count="1" max_count="1" chance="100"/><!--Package: +4 Cloak of Protection (Time-limited)-->
			<capsuled_item id="96225" min_count="1" max_count="1" chance="100"/><!--Herphah's Equipment Pack Lv. 70 (Time-limited)-->
		</capsuled_items>
	</etcitem>
	<etcitem id="96225" name="Herphah's Equipment Pack Lv. 70 (Time-limited)" add_name="Sealed">
		<set name="icon" value="icon.etc_exchange_box_i00"/>
		<set name="stackable" value="true"/>
		<set name="crystal_type" value="NONE"/>
		<set name="tradeable" value="false"/>
		<set name="dropable" value="false"/>
		<set name="privatestoreable" value="false"/>
		<set name="sellable" value="false"/>
		<set name="clan_warehouseable" value="false"/>
		<set name="freightable" value="true"/>
		<set name="type" value="EXTRACTABLE"/>
		<capsuled_items>
			<capsuled_item id="96200" min_count="1" max_count="1" chance="100"/><!--Package: +4 Talisman of Authority (Time-limited)-->
			<capsuled_item id="96226" min_count="1" max_count="1" chance="100"/><!--Herphah's Equipment Pack Lv. 74 (Time-limited)-->
		</capsuled_items>
	</etcitem>
	<etcitem id="96226" name="Herphah's Equipment Pack Lv. 74 (Time-limited)" add_name="Sealed">
		<set name="icon" value="icon.etc_exchange_box_i00"/>
		<set name="stackable" value="true"/>
		<set name="crystal_type" value="NONE"/>
		<set name="tradeable" value="false"/>
		<set name="dropable" value="false"/>
		<set name="privatestoreable" value="false"/>
		<set name="sellable" value="false"/>
		<set name="clan_warehouseable" value="false"/>
		<set name="freightable" value="true"/>
		<set name="type" value="EXTRACTABLE"/>
		<capsuled_items>
			<capsuled_item id="96201" min_count="1" max_count="1" chance="100"/><!--Package: Einhasad's Pendant Lv. 2 (Time-limited)-->
			<capsuled_item id="96227" min_count="1" max_count="1" chance="100"/><!--Herphah's Equipment Pack Lv. 76 (Time-limited)-->
		</capsuled_items>
	</etcitem>
	<etcitem id="96227" name="Herphah's Equipment Pack Lv. 76 (Time-limited)" add_name="Sealed">
		<set name="icon" value="icon.etc_exchange_box_i00"/>
		<set name="stackable" value="true"/>
		<set name="crystal_type" value="NONE"/>
		<set name="tradeable" value="false"/>
		<set name="dropable" value="false"/>
		<set name="privatestoreable" value="false"/>
		<set name="sellable" value="false"/>
		<set name="clan_warehouseable" value="false"/>
		<set name="freightable" value="true"/>
		<set name="type" value="EXTRACTABLE"/>
		<capsuled_items>
			<capsuled_item id="96202" min_count="1" max_count="1" chance="100"/><!--Package: +4 Circlet of Hero (Time-limited)-->
		</capsuled_items>
	</etcitem>
	<etcitem id="96228" name="Special Growth Pack Lv. 85 (Time-limited)" add_name="Sealed">
		<set name="icon" value="icon.event_hero_treasure_box_blue"/>
		<set name="stackable" value="true"/>
		<set name="crystal_type" value="NONE"/>
		<set name="tradeable" value="false"/>
		<set name="dropable" value="false"/>
		<set name="privatestoreable" value="false"/>
		<set name="sellable" value="false"/>
		<set name="clan_warehouseable" value="false"/>
		<set name="freightable" value="true"/>
		<set name="type" value="EXTRACTABLE"/>
		<capsuled_items>
			<capsuled_item id="93338" min_count="7" max_count="7" chance="100"/><!--High-grade Red Lantern (Time-limited)-->
			<capsuled_item id="96229" min_count="1" max_count="1" chance="100"/><!--Special Growth Pack Lv. 86 (Time-limited)-->
		</capsuled_items>
	</etcitem>
	<etcitem id="96229" name="Special Growth Pack Lv. 86 (Time-limited)" add_name="Sealed">
		<set name="icon" value="icon.event_hero_treasure_box_blue"/>
		<set name="stackable" value="true"/>
		<set name="crystal_type" value="NONE"/>
		<set name="tradeable" value="false"/>
		<set name="dropable" value="false"/>
		<set name="privatestoreable" value="false"/>
		<set name="sellable" value="false"/>
		<set name="clan_warehouseable" value="false"/>
		<set name="freightable" value="true"/>
		<set name="type" value="EXTRACTABLE"/>
		<capsuled_items>
			<capsuled_item id="93338" min_count="11" max_count="11" chance="100"/><!--High-grade Red Lantern (Time-limited)-->
			<capsuled_item id="96230" min_count="1" max_count="1" chance="100"/><!--Special Growth Pack Lv. 87 (Time-limited)-->
		</capsuled_items>
	</etcitem>
	<etcitem id="96230" name="Special Growth Pack Lv. 87 (Time-limited)" add_name="Sealed">
		<set name="icon" value="icon.event_hero_treasure_box_blue"/>
		<set name="stackable" value="true"/>
		<set name="crystal_type" value="NONE"/>
		<set name="tradeable" value="false"/>
		<set name="dropable" value="false"/>
		<set name="privatestoreable" value="false"/>
		<set name="sellable" value="false"/>
		<set name="clan_warehouseable" value="false"/>
		<set name="freightable" value="true"/>
		<set name="type" value="EXTRACTABLE"/>
		<capsuled_items>
			<capsuled_item id="93338" min_count="20" max_count="20" chance="100"/><!--High-grade Red Lantern (Time-limited)-->
			<capsuled_item id="96231" min_count="1" max_count="1" chance="100"/><!--Special Growth Pack Lv. 88 (Time-limited)-->
		</capsuled_items>
	</etcitem>
	<etcitem id="96231" name="Special Growth Pack Lv. 88 (Time-limited)" add_name="Sealed">
		<set name="icon" value="icon.event_hero_treasure_box_blue"/>
		<set name="stackable" value="true"/>
		<set name="crystal_type" value="NONE"/>
		<set name="tradeable" value="false"/>
		<set name="dropable" value="false"/>
		<set name="privatestoreable" value="false"/>
		<set name="sellable" value="false"/>
		<set name="clan_warehouseable" value="false"/>
		<set name="freightable" value="true"/>
		<set name="type" value="EXTRACTABLE"/>
		<capsuled_items>
			<capsuled_item id="93338" min_count="41" max_count="41" chance="100"/><!--High-grade Red Lantern (Time-limited)-->
			<capsuled_item id="96232" min_count="1" max_count="1" chance="100"/><!--Special Growth Pack Lv. 89 (Time-limited)-->
		</capsuled_items>
	</etcitem>
	<etcitem id="96232" name="Special Growth Pack Lv. 89 (Time-limited)" add_name="Sealed">
		<set name="icon" value="icon.event_hero_treasure_box_blue"/>
		<set name="stackable" value="true"/>
		<set name="crystal_type" value="NONE"/>
		<set name="tradeable" value="false"/>
		<set name="dropable" value="false"/>
		<set name="privatestoreable" value="false"/>
		<set name="sellable" value="false"/>
		<set name="clan_warehouseable" value="false"/>
		<set name="freightable" value="true"/>
		<set name="type" value="EXTRACTABLE"/>
		<capsuled_items>
			<capsuled_item id="93338" min_count="123" max_count="123" chance="100"/><!--High-grade Red Lantern (Time-limited)-->
		</capsuled_items>
	</etcitem>
	<etcitem id="96233" name="Enhanced Growth Pack Lv. 55 (Time-limited)" add_name="Sealed">
		<set name="icon" value="icon.event_hero_treasure_box_i00"/>
		<set name="stackable" value="true"/>
		<set name="crystal_type" value="NONE"/>
		<set name="tradeable" value="false"/>
		<set name="dropable" value="false"/>
		<set name="privatestoreable" value="false"/>
		<set name="sellable" value="false"/>
		<set name="clan_warehouseable" value="false"/>
		<set name="freightable" value="true"/>
		<set name="type" value="EXTRACTABLE"/>
		<capsuled_items>
			<capsuled_item id="91671" min_count="1" max_count="1" chance="100"/><!--Green Lantern (Time-limited)-->
			<capsuled_item id="96234" min_count="1" max_count="1" chance="100"/><!--Enhanced Growth Pack Lv. 56 (Time-limited)-->
		</capsuled_items>
	</etcitem>
	<etcitem id="96234" name="Enhanced Growth Pack Lv. 56 (Time-limited)" add_name="Sealed">
		<set name="icon" value="icon.event_hero_treasure_box_i00"/>
		<set name="stackable" value="true"/>
		<set name="crystal_type" value="NONE"/>
		<set name="tradeable" value="false"/>
		<set name="dropable" value="false"/>
		<set name="privatestoreable" value="false"/>
		<set name="sellable" value="false"/>
		<set name="clan_warehouseable" value="false"/>
		<set name="freightable" value="true"/>
		<set name="type" value="EXTRACTABLE"/>
		<capsuled_items>
			<capsuled_item id="91671" min_count="2" max_count="2" chance="100"/><!--Green Lantern (Time-limited)-->
			<capsuled_item id="96235" min_count="1" max_count="1" chance="100"/><!--Enhanced Growth Pack Lv. 57 (Time-limited)-->
		</capsuled_items>
	</etcitem>
	<etcitem id="96235" name="Enhanced Growth Pack Lv. 57 (Time-limited)" add_name="Sealed">
		<set name="icon" value="icon.event_hero_treasure_box_i00"/>
		<set name="stackable" value="true"/>
		<set name="crystal_type" value="NONE"/>
		<set name="tradeable" value="false"/>
		<set name="dropable" value="false"/>
		<set name="privatestoreable" value="false"/>
		<set name="sellable" value="false"/>
		<set name="clan_warehouseable" value="false"/>
		<set name="freightable" value="true"/>
		<set name="type" value="EXTRACTABLE"/>
		<capsuled_items>
			<capsuled_item id="91671" min_count="3" max_count="3" chance="100"/><!--Green Lantern (Time-limited)-->
			<capsuled_item id="96236" min_count="1" max_count="1" chance="100"/><!--Enhanced Growth Pack Lv. 58 (Time-limited)-->
		</capsuled_items>
	</etcitem>
	<etcitem id="96236" name="Enhanced Growth Pack Lv. 58 (Time-limited)" add_name="Sealed">
		<set name="icon" value="icon.event_hero_treasure_box_i00"/>
		<set name="stackable" value="true"/>
		<set name="crystal_type" value="NONE"/>
		<set name="tradeable" value="false"/>
		<set name="dropable" value="false"/>
		<set name="privatestoreable" value="false"/>
		<set name="sellable" value="false"/>
		<set name="clan_warehouseable" value="false"/>
		<set name="freightable" value="true"/>
		<set name="type" value="EXTRACTABLE"/>
		<capsuled_items>
			<capsuled_item id="91671" min_count="4" max_count="4" chance="100"/><!--Green Lantern (Time-limited)-->
			<capsuled_item id="96237" min_count="1" max_count="1" chance="100"/><!--Enhanced Growth Pack Lv. 59 (Time-limited)-->
		</capsuled_items>
	</etcitem>
	<etcitem id="96237" name="Enhanced Growth Pack Lv. 59 (Time-limited)" add_name="Sealed">
		<set name="icon" value="icon.event_hero_treasure_box_i00"/>
		<set name="stackable" value="true"/>
		<set name="crystal_type" value="NONE"/>
		<set name="tradeable" value="false"/>
		<set name="dropable" value="false"/>
		<set name="privatestoreable" value="false"/>
		<set name="sellable" value="false"/>
		<set name="clan_warehouseable" value="false"/>
		<set name="freightable" value="true"/>
		<set name="type" value="EXTRACTABLE"/>
		<capsuled_items>
			<capsuled_item id="91671" min_count="4" max_count="4" chance="100"/><!--Green Lantern (Time-limited)-->
			<capsuled_item id="96238" min_count="1" max_count="1" chance="100"/><!--Enhanced Growth Pack Lv. 60 (Time-limited)-->
		</capsuled_items>
	</etcitem>
	<etcitem id="96238" name="Enhanced Growth Pack Lv. 60 (Time-limited)" add_name="Sealed">
		<set name="icon" value="icon.event_hero_treasure_box_i00"/>
		<set name="stackable" value="true"/>
		<set name="crystal_type" value="NONE"/>
		<set name="tradeable" value="false"/>
		<set name="dropable" value="false"/>
		<set name="privatestoreable" value="false"/>
		<set name="sellable" value="false"/>
		<set name="clan_warehouseable" value="false"/>
		<set name="freightable" value="true"/>
		<set name="type" value="EXTRACTABLE"/>
		<capsuled_items>
			<capsuled_item id="91670" min_count="2" max_count="2" chance="100"/><!--Blue Lantern (Time-limited)-->
			<capsuled_item id="96239" min_count="1" max_count="1" chance="100"/><!--Enhanced Growth Pack Lv. 61 (Time-limited)-->
		</capsuled_items>
	</etcitem>
	<etcitem id="96239" name="Enhanced Growth Pack Lv. 61 (Time-limited)" add_name="Sealed">
		<set name="icon" value="icon.event_hero_treasure_box_i00"/>
		<set name="stackable" value="true"/>
		<set name="crystal_type" value="NONE"/>
		<set name="tradeable" value="false"/>
		<set name="dropable" value="false"/>
		<set name="privatestoreable" value="false"/>
		<set name="sellable" value="false"/>
		<set name="clan_warehouseable" value="false"/>
		<set name="freightable" value="true"/>
		<set name="type" value="EXTRACTABLE"/>
		<capsuled_items>
			<capsuled_item id="91670" min_count="3" max_count="3" chance="100"/><!--Blue Lantern (Time-limited)-->
			<capsuled_item id="96240" min_count="1" max_count="1" chance="100"/><!--Enhanced Growth Pack Lv. 62 (Time-limited)-->
		</capsuled_items>
	</etcitem>
	<etcitem id="96240" name="Enhanced Growth Pack Lv. 62 (Time-limited)" add_name="Sealed">
		<set name="icon" value="icon.event_hero_treasure_box_i00"/>
		<set name="stackable" value="true"/>
		<set name="crystal_type" value="NONE"/>
		<set name="tradeable" value="false"/>
		<set name="dropable" value="false"/>
		<set name="privatestoreable" value="false"/>
		<set name="sellable" value="false"/>
		<set name="clan_warehouseable" value="false"/>
		<set name="freightable" value="true"/>
		<set name="type" value="EXTRACTABLE"/>
		<capsuled_items>
			<capsuled_item id="91670" min_count="4" max_count="4" chance="100"/><!--Blue Lantern (Time-limited)-->
			<capsuled_item id="96241" min_count="1" max_count="1" chance="100"/><!--Enhanced Growth Pack Lv. 63 (Time-limited)-->
		</capsuled_items>
	</etcitem>
	<etcitem id="96241" name="Enhanced Growth Pack Lv. 63 (Time-limited)" add_name="Sealed">
		<set name="icon" value="icon.event_hero_treasure_box_i00"/>
		<set name="stackable" value="true"/>
		<set name="crystal_type" value="NONE"/>
		<set name="tradeable" value="false"/>
		<set name="dropable" value="false"/>
		<set name="privatestoreable" value="false"/>
		<set name="sellable" value="false"/>
		<set name="clan_warehouseable" value="false"/>
		<set name="freightable" value="true"/>
		<set name="type" value="EXTRACTABLE"/>
		<capsuled_items>
			<capsuled_item id="91670" min_count="5" max_count="5" chance="100"/><!--Blue Lantern (Time-limited)-->
			<capsuled_item id="96242" min_count="1" max_count="1" chance="100"/><!--Enhanced Growth Pack Lv. 64 (Time-limited)-->
		</capsuled_items>
	</etcitem>
	<etcitem id="96242" name="Enhanced Growth Pack Lv. 64 (Time-limited)" add_name="Sealed">
		<set name="icon" value="icon.event_hero_treasure_box_i00"/>
		<set name="stackable" value="true"/>
		<set name="crystal_type" value="NONE"/>
		<set name="tradeable" value="false"/>
		<set name="dropable" value="false"/>
		<set name="privatestoreable" value="false"/>
		<set name="sellable" value="false"/>
		<set name="clan_warehouseable" value="false"/>
		<set name="freightable" value="true"/>
		<set name="type" value="EXTRACTABLE"/>
		<capsuled_items>
			<capsuled_item id="91670" min_count="6" max_count="6" chance="100"/><!--Blue Lantern (Time-limited)-->
			<capsuled_item id="96243" min_count="1" max_count="1" chance="100"/><!--Enhanced Growth Pack Lv. 65 (Time-limited)-->
		</capsuled_items>
	</etcitem>
	<etcitem id="96243" name="Enhanced Growth Pack Lv. 65 (Time-limited)" add_name="Sealed">
		<set name="icon" value="icon.event_hero_treasure_box_i00"/>
		<set name="stackable" value="true"/>
		<set name="crystal_type" value="NONE"/>
		<set name="tradeable" value="false"/>
		<set name="dropable" value="false"/>
		<set name="privatestoreable" value="false"/>
		<set name="sellable" value="false"/>
		<set name="clan_warehouseable" value="false"/>
		<set name="freightable" value="true"/>
		<set name="type" value="EXTRACTABLE"/>
		<capsuled_items>
			<capsuled_item id="91670" min_count="7" max_count="7" chance="100"/><!--Blue Lantern (Time-limited)-->
			<capsuled_item id="96244" min_count="1" max_count="1" chance="100"/><!--Enhanced Growth Pack Lv. 66 (Time-limited)-->
		</capsuled_items>
	</etcitem>
	<etcitem id="96244" name="Enhanced Growth Pack Lv. 66 (Time-limited)" add_name="Sealed">
		<set name="icon" value="icon.event_hero_treasure_box_i00"/>
		<set name="stackable" value="true"/>
		<set name="crystal_type" value="NONE"/>
		<set name="tradeable" value="false"/>
		<set name="dropable" value="false"/>
		<set name="privatestoreable" value="false"/>
		<set name="sellable" value="false"/>
		<set name="clan_warehouseable" value="false"/>
		<set name="freightable" value="true"/>
		<set name="type" value="EXTRACTABLE"/>
		<capsuled_items>
			<capsuled_item id="91670" min_count="8" max_count="8" chance="100"/><!--Blue Lantern (Time-limited)-->
			<capsuled_item id="96245" min_count="1" max_count="1" chance="100"/><!--Enhanced Growth Pack Lv. 67 (Time-limited)-->
		</capsuled_items>
	</etcitem>
	<etcitem id="96245" name="Enhanced Growth Pack Lv. 67 (Time-limited)" add_name="Sealed">
		<set name="icon" value="icon.event_hero_treasure_box_i00"/>
		<set name="stackable" value="true"/>
		<set name="crystal_type" value="NONE"/>
		<set name="tradeable" value="false"/>
		<set name="dropable" value="false"/>
		<set name="privatestoreable" value="false"/>
		<set name="sellable" value="false"/>
		<set name="clan_warehouseable" value="false"/>
		<set name="freightable" value="true"/>
		<set name="type" value="EXTRACTABLE"/>
		<capsuled_items>
			<capsuled_item id="91670" min_count="10" max_count="10" chance="100"/><!--Blue Lantern (Time-limited)-->
			<capsuled_item id="96246" min_count="1" max_count="1" chance="100"/><!--Enhanced Growth Pack Lv. 68 (Time-limited)-->
		</capsuled_items>
	</etcitem>
	<etcitem id="96246" name="Enhanced Growth Pack Lv. 68 (Time-limited)" add_name="Sealed">
		<set name="icon" value="icon.event_hero_treasure_box_i00"/>
		<set name="stackable" value="true"/>
		<set name="crystal_type" value="NONE"/>
		<set name="tradeable" value="false"/>
		<set name="dropable" value="false"/>
		<set name="privatestoreable" value="false"/>
		<set name="sellable" value="false"/>
		<set name="clan_warehouseable" value="false"/>
		<set name="freightable" value="true"/>
		<set name="type" value="EXTRACTABLE"/>
		<capsuled_items>
			<capsuled_item id="91670" min_count="13" max_count="13" chance="100"/><!--Blue Lantern (Time-limited)-->
			<capsuled_item id="96247" min_count="1" max_count="1" chance="100"/><!--Enhanced Growth Pack Lv. 69 (Time-limited)-->
		</capsuled_items>
	</etcitem>
	<etcitem id="96247" name="Enhanced Growth Pack Lv. 69 (Time-limited)" add_name="Sealed">
		<set name="icon" value="icon.event_hero_treasure_box_i00"/>
		<set name="stackable" value="true"/>
		<set name="crystal_type" value="NONE"/>
		<set name="tradeable" value="false"/>
		<set name="dropable" value="false"/>
		<set name="privatestoreable" value="false"/>
		<set name="sellable" value="false"/>
		<set name="clan_warehouseable" value="false"/>
		<set name="freightable" value="true"/>
		<set name="type" value="EXTRACTABLE"/>
		<capsuled_items>
			<capsuled_item id="91670" min_count="15" max_count="15" chance="100"/><!--Blue Lantern (Time-limited)-->
			<capsuled_item id="96248" min_count="1" max_count="1" chance="100"/><!--Enhanced Growth Pack Lv. 70 (Time-limited)-->
		</capsuled_items>
	</etcitem>
	<etcitem id="96248" name="Enhanced Growth Pack Lv. 70 (Time-limited)" add_name="Sealed">
		<set name="icon" value="icon.event_hero_treasure_box_i00"/>
		<set name="stackable" value="true"/>
		<set name="crystal_type" value="NONE"/>
		<set name="tradeable" value="false"/>
		<set name="dropable" value="false"/>
		<set name="privatestoreable" value="false"/>
		<set name="sellable" value="false"/>
		<set name="clan_warehouseable" value="false"/>
		<set name="freightable" value="true"/>
		<set name="type" value="EXTRACTABLE"/>
		<capsuled_items>
			<capsuled_item id="91670" min_count="19" max_count="19" chance="100"/><!--Blue Lantern (Time-limited)-->
			<capsuled_item id="96249" min_count="1" max_count="1" chance="100"/><!--Enhanced Growth Pack Lv. 71 (Time-limited)-->
		</capsuled_items>
	</etcitem>
	<etcitem id="96249" name="Enhanced Growth Pack Lv. 71 (Time-limited)" add_name="Sealed">
		<set name="icon" value="icon.event_hero_treasure_box_i00"/>
		<set name="stackable" value="true"/>
		<set name="crystal_type" value="NONE"/>
		<set name="tradeable" value="false"/>
		<set name="dropable" value="false"/>
		<set name="privatestoreable" value="false"/>
		<set name="sellable" value="false"/>
		<set name="clan_warehouseable" value="false"/>
		<set name="freightable" value="true"/>
		<set name="type" value="EXTRACTABLE"/>
		<capsuled_items>
			<capsuled_item id="91670" min_count="24" max_count="24" chance="100"/><!--Blue Lantern (Time-limited)-->
			<capsuled_item id="96250" min_count="1" max_count="1" chance="100"/><!--Enhanced Growth Pack Lv. 72 (Time-limited)-->
		</capsuled_items>
	</etcitem>
	<etcitem id="96250" name="Enhanced Growth Pack Lv. 72 (Time-limited)" add_name="Sealed">
		<set name="icon" value="icon.event_hero_treasure_box_i00"/>
		<set name="stackable" value="true"/>
		<set name="crystal_type" value="NONE"/>
		<set name="tradeable" value="false"/>
		<set name="dropable" value="false"/>
		<set name="privatestoreable" value="false"/>
		<set name="sellable" value="false"/>
		<set name="clan_warehouseable" value="false"/>
		<set name="freightable" value="true"/>
		<set name="type" value="EXTRACTABLE"/>
		<capsuled_items>
			<capsuled_item id="91668" min_count="3" max_count="3" chance="100"/><!--Red Lantern (Time-limited)-->
			<capsuled_item id="96251" min_count="1" max_count="1" chance="100"/><!--Enhanced Growth Pack Lv. 73 (Time-limited)-->
		</capsuled_items>
	</etcitem>
	<etcitem id="96251" name="Enhanced Growth Pack Lv. 73 (Time-limited)" add_name="Sealed">
		<set name="icon" value="icon.event_hero_treasure_box_i00"/>
		<set name="stackable" value="true"/>
		<set name="crystal_type" value="NONE"/>
		<set name="tradeable" value="false"/>
		<set name="dropable" value="false"/>
		<set name="privatestoreable" value="false"/>
		<set name="sellable" value="false"/>
		<set name="clan_warehouseable" value="false"/>
		<set name="freightable" value="true"/>
		<set name="type" value="EXTRACTABLE"/>
		<capsuled_items>
			<capsuled_item id="91668" min_count="3" max_count="3" chance="100"/><!--Red Lantern (Time-limited)-->
			<capsuled_item id="96252" min_count="1" max_count="1" chance="100"/><!--Enhanced Growth Pack Lv. 74 (Time-limited)-->
		</capsuled_items>
	</etcitem>
	<etcitem id="96252" name="Enhanced Growth Pack Lv. 74 (Time-limited)" add_name="Sealed">
		<set name="icon" value="icon.event_hero_treasure_box_i00"/>
		<set name="stackable" value="true"/>
		<set name="crystal_type" value="NONE"/>
		<set name="tradeable" value="false"/>
		<set name="dropable" value="false"/>
		<set name="privatestoreable" value="false"/>
		<set name="sellable" value="false"/>
		<set name="clan_warehouseable" value="false"/>
		<set name="freightable" value="true"/>
		<set name="type" value="EXTRACTABLE"/>
		<capsuled_items>
			<capsuled_item id="91668" min_count="4" max_count="4" chance="100"/><!--Red Lantern (Time-limited)-->
			<capsuled_item id="96253" min_count="1" max_count="1" chance="100"/><!--Enhanced Growth Pack Lv. 75 (Time-limited)-->
		</capsuled_items>
	</etcitem>
	<etcitem id="96253" name="Enhanced Growth Pack Lv. 75 (Time-limited)" add_name="Sealed">
		<set name="icon" value="icon.event_hero_treasure_box_i00"/>
		<set name="stackable" value="true"/>
		<set name="crystal_type" value="NONE"/>
		<set name="tradeable" value="false"/>
		<set name="dropable" value="false"/>
		<set name="privatestoreable" value="false"/>
		<set name="sellable" value="false"/>
		<set name="clan_warehouseable" value="false"/>
		<set name="freightable" value="true"/>
		<set name="type" value="EXTRACTABLE"/>
		<capsuled_items>
			<capsuled_item id="91668" min_count="6" max_count="6" chance="100"/><!--Red Lantern (Time-limited)-->
			<capsuled_item id="96254" min_count="1" max_count="1" chance="100"/><!--Enhanced Growth Pack Lv. 76 (Time-limited)-->
		</capsuled_items>
	</etcitem>
	<etcitem id="96254" name="Enhanced Growth Pack Lv. 76 (Time-limited)" add_name="Sealed">
		<set name="icon" value="icon.event_hero_treasure_box_i00"/>
		<set name="stackable" value="true"/>
		<set name="crystal_type" value="NONE"/>
		<set name="tradeable" value="false"/>
		<set name="dropable" value="false"/>
		<set name="privatestoreable" value="false"/>
		<set name="sellable" value="false"/>
		<set name="clan_warehouseable" value="false"/>
		<set name="freightable" value="true"/>
		<set name="type" value="EXTRACTABLE"/>
		<capsuled_items>
			<capsuled_item id="91668" min_count="7" max_count="7" chance="100"/><!--Red Lantern (Time-limited)-->
			<capsuled_item id="96255" min_count="1" max_count="1" chance="100"/><!--Enhanced Growth Pack Lv. 77 (Time-limited)-->
		</capsuled_items>
	</etcitem>
	<etcitem id="96255" name="Enhanced Growth Pack Lv. 77 (Time-limited)" add_name="Sealed">
		<set name="icon" value="icon.event_hero_treasure_box_i00"/>
		<set name="stackable" value="true"/>
		<set name="crystal_type" value="NONE"/>
		<set name="tradeable" value="false"/>
		<set name="dropable" value="false"/>
		<set name="privatestoreable" value="false"/>
		<set name="sellable" value="false"/>
		<set name="clan_warehouseable" value="false"/>
		<set name="freightable" value="true"/>
		<set name="type" value="EXTRACTABLE"/>
		<capsuled_items>
			<capsuled_item id="91668" min_count="8" max_count="8" chance="100"/><!--Red Lantern (Time-limited)-->
			<capsuled_item id="96256" min_count="1" max_count="1" chance="100"/><!--Enhanced Growth Pack Lv. 78 (Time-limited)-->
		</capsuled_items>
	</etcitem>
	<etcitem id="96256" name="Enhanced Growth Pack Lv. 78 (Time-limited)" add_name="Sealed">
		<set name="icon" value="icon.event_hero_treasure_box_i00"/>
		<set name="stackable" value="true"/>
		<set name="crystal_type" value="NONE"/>
		<set name="tradeable" value="false"/>
		<set name="dropable" value="false"/>
		<set name="privatestoreable" value="false"/>
		<set name="sellable" value="false"/>
		<set name="clan_warehouseable" value="false"/>
		<set name="freightable" value="true"/>
		<set name="type" value="EXTRACTABLE"/>
		<capsuled_items>
			<capsuled_item id="91668" min_count="10" max_count="10" chance="100"/><!--Red Lantern (Time-limited)-->
			<capsuled_item id="96257" min_count="1" max_count="1" chance="100"/><!--Enhanced Growth Pack Lv. 79 (Time-limited)-->
		</capsuled_items>
	</etcitem>
	<etcitem id="96257" name="Enhanced Growth Pack Lv. 79 (Time-limited)" add_name="Sealed">
		<set name="icon" value="icon.event_hero_treasure_box_i00"/>
		<set name="stackable" value="true"/>
		<set name="crystal_type" value="NONE"/>
		<set name="tradeable" value="false"/>
		<set name="dropable" value="false"/>
		<set name="privatestoreable" value="false"/>
		<set name="sellable" value="false"/>
		<set name="clan_warehouseable" value="false"/>
		<set name="freightable" value="true"/>
		<set name="type" value="EXTRACTABLE"/>
		<capsuled_items>
			<capsuled_item id="91668" min_count="13" max_count="13" chance="100"/><!--Red Lantern (Time-limited)-->
			<capsuled_item id="96258" min_count="1" max_count="1" chance="100"/><!--Enhanced Growth Pack Lv. 80 (Time-limited)-->
		</capsuled_items>
	</etcitem>
	<etcitem id="96258" name="Enhanced Growth Pack Lv. 80 (Time-limited)" add_name="Sealed">
		<set name="icon" value="icon.event_hero_treasure_box_i00"/>
		<set name="stackable" value="true"/>
		<set name="crystal_type" value="NONE"/>
		<set name="tradeable" value="false"/>
		<set name="dropable" value="false"/>
		<set name="privatestoreable" value="false"/>
		<set name="sellable" value="false"/>
		<set name="clan_warehouseable" value="false"/>
		<set name="freightable" value="true"/>
		<set name="type" value="EXTRACTABLE"/>
		<capsuled_items>
			<capsuled_item id="91668" min_count="17" max_count="17" chance="100"/><!--Red Lantern (Time-limited)-->
			<capsuled_item id="96259" min_count="1" max_count="1" chance="100"/><!--Enhanced Growth Pack Lv. 81 (Time-limited)-->
		</capsuled_items>
	</etcitem>
	<etcitem id="96259" name="Enhanced Growth Pack Lv. 81 (Time-limited)" add_name="Sealed">
		<set name="icon" value="icon.event_hero_treasure_box_i00"/>
		<set name="stackable" value="true"/>
		<set name="crystal_type" value="NONE"/>
		<set name="tradeable" value="false"/>
		<set name="dropable" value="false"/>
		<set name="privatestoreable" value="false"/>
		<set name="sellable" value="false"/>
		<set name="clan_warehouseable" value="false"/>
		<set name="freightable" value="true"/>
		<set name="type" value="EXTRACTABLE"/>
		<capsuled_items>
			<capsuled_item id="93338" min_count="2" max_count="2" chance="100"/><!--High-grade Red Lantern (Time-limited)-->
			<capsuled_item id="96260" min_count="1" max_count="1" chance="100"/><!--Enhanced Growth Pack Lv. 82 (Time-limited)-->
		</capsuled_items>
	</etcitem>
	<etcitem id="96260" name="Enhanced Growth Pack Lv. 82 (Time-limited)" add_name="Sealed">
		<set name="icon" value="icon.event_hero_treasure_box_i00"/>
		<set name="stackable" value="true"/>
		<set name="crystal_type" value="NONE"/>
		<set name="tradeable" value="false"/>
		<set name="dropable" value="false"/>
		<set name="privatestoreable" value="false"/>
		<set name="sellable" value="false"/>
		<set name="clan_warehouseable" value="false"/>
		<set name="freightable" value="true"/>
		<set name="type" value="EXTRACTABLE"/>
		<capsuled_items>
			<capsuled_item id="93338" min_count="3" max_count="3" chance="100"/><!--High-grade Red Lantern (Time-limited)-->
			<capsuled_item id="96261" min_count="1" max_count="1" chance="100"/><!--Enhanced Growth Pack Lv. 83 (Time-limited)-->
		</capsuled_items>
	</etcitem>
	<etcitem id="96261" name="Enhanced Growth Pack Lv. 83 (Time-limited)" add_name="Sealed">
		<set name="icon" value="icon.event_hero_treasure_box_i00"/>
		<set name="stackable" value="true"/>
		<set name="crystal_type" value="NONE"/>
		<set name="tradeable" value="false"/>
		<set name="dropable" value="false"/>
		<set name="privatestoreable" value="false"/>
		<set name="sellable" value="false"/>
		<set name="clan_warehouseable" value="false"/>
		<set name="freightable" value="true"/>
		<set name="type" value="EXTRACTABLE"/>
		<capsuled_items>
			<capsuled_item id="93338" min_count="4" max_count="4" chance="100"/><!--High-grade Red Lantern (Time-limited)-->
			<capsuled_item id="96262" min_count="1" max_count="1" chance="100"/><!--Enhanced Growth Pack Lv. 84 (Time-limited)-->
		</capsuled_items>
	</etcitem>
	<etcitem id="96262" name="Enhanced Growth Pack Lv. 84 (Time-limited)" add_name="Sealed">
		<set name="icon" value="icon.event_hero_treasure_box_i00"/>
		<set name="stackable" value="true"/>
		<set name="crystal_type" value="NONE"/>
		<set name="tradeable" value="false"/>
		<set name="dropable" value="false"/>
		<set name="privatestoreable" value="false"/>
		<set name="sellable" value="false"/>
		<set name="clan_warehouseable" value="false"/>
		<set name="freightable" value="true"/>
		<set name="type" value="EXTRACTABLE"/>
		<capsuled_items>
			<capsuled_item id="93338" min_count="7" max_count="7" chance="100"/><!--High-grade Red Lantern (Time-limited)-->
		</capsuled_items>
	</etcitem>
	<etcitem id="96263" name="Hellbound's Treasure Chest (Time-limited)" add_name="Sealed">
		<set name="icon" value="icon.present_of_destination_event"/>
		<set name="stackable" value="true"/>
		<set name="crystal_type" value="NONE"/>
		<set name="tradeable" value="false"/>
		<set name="dropable" value="false"/>
		<set name="privatestoreable" value="false"/>
		<set name="sellable" value="false"/>
		<set name="clan_warehouseable" value="false"/>
		<set name="mailable" value="false"/>
		<set name="type" value="EXTRACTABLE"/>
		<create_items>
			<create_item id="93387" count="1" chance="0.01"/><!--Spellbook: Ultimate Death Knight Transformation--><!--TODO: Check chance-->
			<create_item id="94498" count="1" chance="0.01"/><!--Spellbook: Titan Champion--><!--TODO: Check chance-->
			<create_item id="95354" count="1" chance="0.01"/><!--Spellbook: Dragon Strike--><!--TODO: Check chance-->
			<create_item id="95347" count="1" chance="0.01"/><!--Spellbook: Rolling Dice--><!--TODO: Check chance-->
			<create_item id="95861" count="1" chance="0.01"/><!--Spellbook: Mechanical Hero--><!--TODO: Check chance-->
			<create_item id="95346" count="1" chance="0.01"/><!--Spellbook: Meteor--><!--TODO: Check chance-->
			<create_item id="94508" count="1" chance="0.01"/><!--Spellbook: Cacophony of War--><!--TODO: Check chance-->
			<create_item id="94862" count="1" chance="0.01"/><!--Spellbook: Exclusion--><!--TODO: Check chance-->
			<create_item id="94863" count="1" chance="0.01"/><!--Spellbook: Dark Disruption--><!--TODO: Check chance-->
			<create_item id="94861" count="1" chance="0.01"/><!--Spellbook: Tranquillity--><!--TODO: Check chance-->
			<create_item id="94668" count="1" chance="0.01"/><!--Spellbook: Pa'agrio's Touch--><!--TODO: Check chance-->
			<create_item id="94840" count="1" chance="0.01"/><!--Breastplate of Protection--><!--TODO: Check chance-->
			<create_item id="94841" count="1" chance="0.01"/><!--Gaiters of Protection--><!--TODO: Check chance-->
			<create_item id="94844" count="1" chance="0.01"/><!--Leather Armor of Protection--><!--TODO: Check chance-->
			<create_item id="94845" count="1" chance="0.01"/><!--Leather Leggings of Protection--><!--TODO: Check chance-->
			<create_item id="94848" count="1" chance="0.01"/><!--Tunic of Protection--><!--TODO: Check chance-->
			<create_item id="94849" count="1" chance="0.01"/><!--Stockings of Protection--><!--TODO: Check chance-->
			<create_item id="95665" count="1" chance="0.01"/><!--Shield of Protection--><!--TODO: Check chance-->
			<create_item id="95663" count="1" chance="0.01"/><!--Sigil of Protection--><!--TODO: Check chance-->
			<create_item id="95933" count="1" chance="0.01"/><!--Gauntlets of Protection--><!--TODO: Check chance-->
			<create_item id="95932" count="1" chance="0.01"/><!--Helmet of Protection--><!--TODO: Check chance-->
			<create_item id="95934" count="1" chance="0.01"/><!--Boots of Protection--><!--TODO: Check chance-->
			<create_item id="95660" count="1" chance="0.01"/><!--Boss' Weapon Pack--><!--TODO: Check chance-->
			<create_item id="49683" count="1" chance="0.01"/><!--Talisman of Baium--><!--TODO: Check chance-->
			<create_item id="91550" count="1" chance="0.01"/><!--Frintezza's Necklace--><!--TODO: Check chance-->
			<create_item id="49580" count="1" chance="0.01"/><!--Baium's Ring--><!--TODO: Check chance-->
			<create_item id="90763" count="1" chance="0.01"/><!--Zaken's Earring--><!--TODO: Check chance-->
			<create_item id="6660" count="1" chance="0.01"/><!--Queen Ant's Ring--><!--TODO: Check chance-->
			<create_item id="6661" count="1" chance="0.01"/><!--Orfen's Earring--><!--TODO: Check chance-->
			<create_item id="6662" count="1" chance="0.01"/><!--Ring of Core--><!--TODO: Check chance-->
			<create_item id="92401" count="1" chance="0.01"/><!--Spellbook: White Guardian--><!--TODO: Check chance-->
			<create_item id="94385" count="1" chance="0.01"/><!--Improved Scroll: Enchant Rare Accessories--><!--TODO: Check chance-->
			<create_item id="94383" count="1" chance="0.01"/><!--Scroll: Enchant Rare Accessories--><!--TODO: Check chance-->
			<create_item id="96357" count="1" chance="0.01"/><!--STR Dye--><!--TODO: Check chance-->
			<create_item id="96377" count="1" chance="0.01"/><!--CON Dye--><!--TODO: Check chance-->
			<create_item id="96417" count="1" chance="0.01"/><!--INT Dye--><!--TODO: Check chance-->
			<create_item id="96397" count="1" chance="0.01"/><!--DEX Dye--><!--TODO: Check chance-->
			<create_item id="96457" count="1" chance="0.01"/><!--WIT Dye--><!--TODO: Check chance-->
			<create_item id="96437" count="1" chance="0.01"/><!--MEN Dye--><!--TODO: Check chance-->
			<create_item id="93739" count="1" chance="0.01"/><!--Package: Giran Seal (1000 pcs.)--><!--TODO: Check chance-->
			<create_item id="94156" count="1" chance="0.01"/><!--Package: Baium Doll Lv. 1--><!--TODO: Check chance-->
			<create_item id="94513" count="1" chance="0.01"/><!--Package: Frintezza Doll Lv. 1--><!--TODO: Check chance-->
			<create_item id="94651" count="1" chance="0.01"/><!--Package: Zaken Doll Lv. 1--><!--TODO: Check chance-->
			<create_item id="94654" count="1" chance="0.01"/><!--Package: Core Doll Lv. 1--><!--TODO: Check chance-->
			<create_item id="94159" count="1" chance="0.01"/><!--Package: Queen Ant Doll Lv. 1--><!--TODO: Check chance-->
			<create_item id="94162" count="1" chance="0.01"/><!--Package: Orfen Doll Lv. 1--><!--TODO: Check chance-->
			<create_item id="95773" count="1" chance="0.01"/><!--Master's Book Chest--><!--TODO: Check chance-->
			<create_item id="94208" count="1" chance="0.01"/><!--Scroll of Blessing--><!--TODO: Check chance-->
			<create_item id="94328" count="1" chance="0.01"/><!--Elixir Powder--><!--TODO: Check chance-->
			<create_item id="91032" count="1" chance="0.01"/><!--Fire Spirit Evolution Stone--><!--TODO: Check chance-->
			<create_item id="91031" count="1" chance="0.01"/><!--Water Spirit Evolution Stone--><!--TODO: Check chance-->
			<create_item id="91033" count="1" chance="0.01"/><!--Wind Spirit Evolution Stone--><!--TODO: Check chance-->
			<create_item id="91034" count="1" chance="0.01"/><!--Earth Spirit Evolution Stone--><!--TODO: Check chance-->
			<create_item id="93255" count="1" chance="0.01"/><!--Improved Scroll: Enchant A-grade Weapon--><!--TODO: Check chance-->
			<create_item id="93256" count="1" chance="0.01"/><!--Improved Scroll: Enchant A-grade Armor--><!--TODO: Check chance-->
			<create_item id="93257" count="1" chance="0.01"/><!--Cursed Scroll: Enchant A-grade Weapon--><!--TODO: Check chance-->
			<create_item id="93258" count="1" chance="0.01"/><!--Cursed Scroll: Enchant A-grade Armor--><!--TODO: Check chance-->
			<create_item id="94717" count="2" chance="0.01"/><!--Hellbound Energy--><!--TODO: Check chance-->
			<create_item id="91076" count="2" chance="0.01"/><!--Venir's Talisman Fragment--><!--TODO: Check chance-->
			<create_item id="94269" count="2" chance="0.01"/><!--Scroll: Boost Attack--><!--TODO: Check chance-->
			<create_item id="94271" count="2" chance="0.01"/><!--Scroll: Boost Defense--><!--TODO: Check chance-->
			<create_item id="49674" count="2" chance="0.01"/><!--XP Growth Scroll--><!--TODO: Check chance-->
			<create_item id="91641" count="10" chance="0.01"/><!--Sayha's Blessing--><!--TODO: Check chance-->
			<create_item id="91690" count="50" chance="0.01"/><!--Special HP Recovery Potion--><!--TODO: Check chance-->
			<create_item id="92314" count="20" chance="0.01"/><!--Giran Seal--><!--TODO: Check chance-->
			<create_item id="92314" count="10" chance="0.01"/><!--Giran Seal--><!--TODO: Check chance-->
			<create_item id="92314" count="5" chance="0.01"/><!--Giran Seal--><!--TODO: Check chance-->
			<create_item id="92314" count="2" chance="0.01"/><!--Giran Seal--><!--TODO: Check chance-->
			<create_item id="92314" count="1" chance="0.01"/><!--Giran Seal--><!--TODO: Check chance-->
		</create_items>
	</etcitem>
	<etcitem id="96264" name="Scratched Key (Time-limited)" add_name="Sealed">
		<set name="icon" value="icon.etc_old_key_i01"/>
		<set name="stackable" value="true"/>
		<set name="crystal_type" value="NONE"/>
		<set name="tradeable" value="false"/>
		<set name="dropable" value="false"/>
		<set name="privatestoreable" value="false"/>
		<set name="sellable" value="false"/>
		<set name="clan_warehouseable" value="false"/>
		<set name="mailable" value="false"/>
	</etcitem>
	<etcitem id="96265" name="Polished Key (Time-limited)" add_name="Sealed">
		<set name="icon" value="icon.etc_old_key_i00"/>
		<set name="stackable" value="true"/>
		<set name="crystal_type" value="NONE"/>
		<set name="tradeable" value="false"/>
		<set name="dropable" value="false"/>
		<set name="privatestoreable" value="false"/>
		<set name="sellable" value="false"/>
		<set name="clan_warehouseable" value="false"/>
		<set name="mailable" value="false"/>
	</etcitem>
	<etcitem id="96266" name="Support Supply Box (Time-limited)" add_name="Sealed">
		<set name="icon" value="icon.etc_treasure_box_i00"/>
		<set name="stackable" value="true"/>
		<set name="crystal_type" value="NONE"/>
		<set name="tradeable" value="false"/>
		<set name="dropable" value="false"/>
		<set name="privatestoreable" value="false"/>
		<set name="sellable" value="false"/>
		<set name="clan_warehouseable" value="false"/>
		<set name="mailable" value="false"/>
		<set name="type" value="EXTRACTABLE"/>
		<create_items>
			<create_item id="95693" count="2" chance="0.01"/><!--Berserker's Scroll (Time-limited)--><!--TODO: Check chance-->
			<create_item id="94380" count="2" chance="0.01"/><!--Scroll: Boost Attack (Time-limited)--><!--TODO: Check chance-->
			<create_item id="94381" count="2" chance="0.01"/><!--Scroll: Boost Defense (Time-limited)--><!--TODO: Check chance-->
			<create_item id="93848" count="7" chance="0.01"/><!--Sayha's Cookie (Time-limited)--><!--TODO: Check chance-->
			<create_item id="90907" count="7" chance="0.01"/><!--Soulshot Ticket--><!--TODO: Check chance-->
			<create_item id="3031" count="70" chance="0.01"/><!--Spirit Ore--><!--TODO: Check chance-->
		</create_items>
	</etcitem>
	<etcitem id="96267" name="Special Support Supply Box (Time-limited)" add_name="Sealed">
		<set name="icon" value="icon.etc_treasure_box_i08"/>
		<set name="stackable" value="true"/>
		<set name="crystal_type" value="NONE"/>
		<set name="tradeable" value="false"/>
		<set name="dropable" value="false"/>
		<set name="privatestoreable" value="false"/>
		<set name="sellable" value="false"/>
		<set name="clan_warehouseable" value="false"/>
		<set name="mailable" value="false"/>
		<set name="type" value="EXTRACTABLE"/>
		<create_items>
			<create_item id="93933" count="1" chance="0.01"/><!--Rare Accessory Pack--><!--TODO: Check chance-->
			<create_item id="94153" count="1" chance="0.01"/><!--Baium Doll Lv. 1--><!--TODO: Check chance-->
			<create_item id="94154" count="1" chance="0.01"/><!--Queen Ant Doll Lv. 1--><!--TODO: Check chance-->
			<create_item id="94155" count="1" chance="0.01"/><!--Orfen Doll Lv. 1--><!--TODO: Check chance-->
			<create_item id="94645" count="1" chance="0.01"/><!--Zaken Doll Lv. 1--><!--TODO: Check chance-->
			<create_item id="94648" count="1" chance="0.01"/><!--Core Doll Lv. 1--><!--TODO: Check chance-->
			<create_item id="94509" count="1" chance="0.01"/><!--Frintezza Doll Lv. 1--><!--TODO: Check chance-->
			<create_item id="93448" count="1" chance="0.01"/><!--A-grade Weapon Coupon--><!--TODO: Check chance-->
			<create_item id="93449" count="1" chance="0.01"/><!--A-grade Armor Coupon--><!--TODO: Check chance-->
			<create_item id="91767" count="1" chance="0.01"/><!--Enchant Kit: Talisman of Aden--><!--TODO: Check chance-->
			<create_item id="92020" count="1" chance="0.01"/><!--Enchant Kit: Talisman of Eva--><!--TODO: Check chance-->
			<create_item id="93685" count="1" chance="0.01"/><!--Enchant Kit: Talisman of Speed--><!--TODO: Check chance-->
			<create_item id="91864" count="1" chance="0.01"/><!--Dragon Belt Pack--><!--TODO: Check chance-->
			<create_item id="94732" count="1" chance="0.01"/><!--Agathion Spirit Exchange Coupon--><!--TODO: Check chance-->
		</create_items>
	</etcitem>
	<weapon id="96268" name="Beleth's Soul Eater">
		<set name="crystal_type" value="A"/>
		<set name="icon" value="icon.staff_of_bereth"/>
		<set name="price" value="26968400"/>
		<set name="grind_point" value="13484200"/>
		<set name="grind_commission" value="269684"/>
		<set name="type" value="BIGBLUNT"/>
		<set name="weight" value="880"/>
		<set name="soulshots" value="2"/>
		<set name="spiritshots" value="2"/>
		<set name="random_damage" value="19"/>
		<set name="freightable" value="true"/>
		<equip>
			<slot id="LEFT_RIGHT_HAND"/>
		</equip>
		<for>
			<add stat="pAtk" order="0x10" value="245"/>
			<add stat="mAtk" order="0x10" value="212"/>
			<set stat="basePAtkSpd" order="0x08" value="325"/>
			<set stat="basePCritRate" order="0x08" value="60"/>
			<add stat="pAccCombat" order="0x10" value="8"/>
		</for>
	</weapon>
	<weapon id="96269" name="Beleth's Soul Eater" add_name="Sealed">
		<set name="crystal_type" value="A"/>
		<set name="icon" value="icon.staff_of_bereth"/>
		<set name="type" value="BIGBLUNT"/>
		<set name="weight" value="880"/>
		<set name="soulshots" value="2"/>
		<set name="spiritshots" value="2"/>
		<set name="random_damage" value="19"/>
		<set name="tradeable" value="false"/>
		<set name="dropable" value="false"/>
		<set name="privatestoreable" value="false"/>
		<set name="clan_warehouseable" value="false"/>
		<set name="freightable" value="true"/>
		<equip>
			<slot id="LEFT_RIGHT_HAND"/>
		</equip>
		<for>
			<add stat="pAtk" order="0x10" value="245"/>
			<add stat="mAtk" order="0x10" value="212"/>
			<set stat="basePAtkSpd" order="0x08" value="325"/>
			<set stat="basePCritRate" order="0x08" value="60"/>
			<add stat="pAccCombat" order="0x10" value="8"/>
		</for>
	</weapon>
	<armor id="96270" name="Dragon Slayer Outfit - Not Available">
		<set name="crystal_type" value="NONE"/>
		<set name="icon" value="icon.dragon_slayer_suit"/>
		<set name="type" value="HEAVY"/>
		<set name="sellable" value="false"/>
		<set name="mailable" value="false"/>
		<equip>
			<slot id="FORMAL_WEAR"/>
		</equip>
	</armor>
	<armor id="96271" name="Test Period 1" add_name="2 min.">
		<set name="crystal_type" value="NONE"/>
		<set name="icon" value="icon.accessory_ring_of_queen_ant_i04"/>
		<set name="type" value="NONE"/>
		<set name="weight" value="150"/>
		<set name="tradeable" value="false"/>
		<set name="dropable" value="false"/>
		<set name="privatestoreable" value="false"/>
		<set name="sellable" value="false"/>
		<set name="clan_warehouseable" value="false"/>
		<set name="mailable" value="false"/>
		<equip>
			<slot id="RIGHT_FINGER"/>
			<slot id="LEFT_FINGER"/>
		</equip>
		<for>
			<add stat="mDef" order="0x10" value="77"/>
			<add stat="maxMp" order="0x60" value="30"/>
		</for>
	</armor>
	<etcitem id="96272" name="Test Period 2" add_name="2 min.">
		<set name="icon" value="icon.scrl_item_unlock"/>
		<set name="crystal_type" value="NONE"/>
		<set name="tradeable" value="false"/>
		<set name="dropable" value="false"/>
		<set name="privatestoreable" value="false"/>
		<set name="sellable" value="false"/>
		<set name="clan_warehouseable" value="false"/>
		<set name="mailable" value="false"/>
	</etcitem>
	<etcitem id="96273" name="Spellbook: Masterpiece Shield">
		<set name="icon" value="icon.etc_magic_book_black_i00"/>
		<set name="stackable" value="true"/>
		<set name="crystal_type" value="NONE"/>
		<set name="sellable" value="false"/>
		<set name="mailable" value="false"/>
	</etcitem>
	<etcitem id="96274" name="Spellbook: Masterpiece Shield" add_name="Sealed">
		<set name="icon" value="icon.etc_magic_book_black_i00"/>
		<set name="stackable" value="true"/>
		<set name="crystal_type" value="NONE"/>
		<set name="tradeable" value="false"/>
		<set name="dropable" value="false"/>
		<set name="privatestoreable" value="false"/>
		<set name="sellable" value="false"/>
		<set name="clan_warehouseable" value="false"/>
		<set name="mailable" value="false"/>
	</etcitem>
	<etcitem id="96275" name="Spellbook: Knight's Power">
		<set name="icon" value="icon.etc_magic_book_black_i00"/>
		<set name="stackable" value="true"/>
		<set name="crystal_type" value="NONE"/>
		<set name="sellable" value="false"/>
		<set name="mailable" value="false"/>
	</etcitem>
	<etcitem id="96276" name="Spellbook: Knight's Power" add_name="Sealed">
		<set name="icon" value="icon.etc_magic_book_black_i00"/>
		<set name="stackable" value="true"/>
		<set name="crystal_type" value="NONE"/>
		<set name="tradeable" value="false"/>
		<set name="dropable" value="false"/>
		<set name="privatestoreable" value="false"/>
		<set name="sellable" value="false"/>
		<set name="clan_warehouseable" value="false"/>
		<set name="mailable" value="false"/>
	</etcitem>
	<etcitem id="96277" name="Spellbook: Knight Assault">
		<set name="icon" value="icon.etc_magic_book_black_i00"/>
		<set name="stackable" value="true"/>
		<set name="crystal_type" value="NONE"/>
		<set name="sellable" value="false"/>
		<set name="mailable" value="false"/>
	</etcitem>
	<etcitem id="96278" name="Spellbook: Knight Assault" add_name="Sealed">
		<set name="icon" value="icon.etc_magic_book_black_i00"/>
		<set name="stackable" value="true"/>
		<set name="crystal_type" value="NONE"/>
		<set name="tradeable" value="false"/>
		<set name="dropable" value="false"/>
		<set name="privatestoreable" value="false"/>
		<set name="sellable" value="false"/>
		<set name="clan_warehouseable" value="false"/>
		<set name="mailable" value="false"/>
	</etcitem>
	<etcitem id="96279" name="Spellbook: Chain Strike (Shock)">
		<set name="icon" value="icon.etc_magic_book_black_i00"/>
		<set name="stackable" value="true"/>
		<set name="crystal_type" value="NONE"/>
		<set name="sellable" value="false"/>
		<set name="mailable" value="false"/>
	</etcitem>
	<etcitem id="96280" name="Spellbook: Chain Strike (Shock)" add_name="Sealed">
		<set name="icon" value="icon.etc_magic_book_black_i00"/>
		<set name="stackable" value="true"/>
		<set name="crystal_type" value="NONE"/>
		<set name="tradeable" value="false"/>
		<set name="dropable" value="false"/>
		<set name="privatestoreable" value="false"/>
		<set name="sellable" value="false"/>
		<set name="clan_warehouseable" value="false"/>
		<set name="mailable" value="false"/>
	</etcitem>
	<etcitem id="96281" name="Spellbook: Shield Throwing">
		<set name="icon" value="icon.etc_magic_book_black_i00"/>
		<set name="stackable" value="true"/>
		<set name="crystal_type" value="NONE"/>
		<set name="sellable" value="false"/>
		<set name="mailable" value="false"/>
	</etcitem>
	<etcitem id="96282" name="Spellbook: Shield Throwing" add_name="Sealed">
		<set name="icon" value="icon.etc_magic_book_black_i00"/>
		<set name="stackable" value="true"/>
		<set name="crystal_type" value="NONE"/>
		<set name="tradeable" value="false"/>
		<set name="dropable" value="false"/>
		<set name="privatestoreable" value="false"/>
		<set name="sellable" value="false"/>
		<set name="clan_warehouseable" value="false"/>
		<set name="mailable" value="false"/>
	</etcitem>
	<etcitem id="96283" name="Spellbook: Power of Life">
		<set name="icon" value="icon.etc_magic_book_black_i00"/>
		<set name="stackable" value="true"/>
		<set name="crystal_type" value="NONE"/>
		<set name="sellable" value="false"/>
		<set name="mailable" value="false"/>
	</etcitem>
	<etcitem id="96284" name="Spellbook: Power of Life" add_name="Sealed">
		<set name="icon" value="icon.etc_magic_book_black_i00"/>
		<set name="stackable" value="true"/>
		<set name="crystal_type" value="NONE"/>
		<set name="tradeable" value="false"/>
		<set name="dropable" value="false"/>
		<set name="privatestoreable" value="false"/>
		<set name="sellable" value="false"/>
		<set name="clan_warehouseable" value="false"/>
		<set name="mailable" value="false"/>
	</etcitem>
	<etcitem id="96285" name="Spellbook: Toughness">
		<set name="icon" value="icon.etc_magic_book_black_i00"/>
		<set name="stackable" value="true"/>
		<set name="crystal_type" value="NONE"/>
		<set name="sellable" value="false"/>
		<set name="mailable" value="false"/>
	</etcitem>
	<etcitem id="96286" name="Spellbook: Toughness" add_name="Sealed">
		<set name="icon" value="icon.etc_magic_book_black_i00"/>
		<set name="stackable" value="true"/>
		<set name="crystal_type" value="NONE"/>
		<set name="tradeable" value="false"/>
		<set name="dropable" value="false"/>
		<set name="privatestoreable" value="false"/>
		<set name="sellable" value="false"/>
		<set name="clan_warehouseable" value="false"/>
		<set name="mailable" value="false"/>
	</etcitem>
	<etcitem id="96287" name="Spellbook: Ultimate Defense Lv. 3">
		<set name="icon" value="icon.etc_magic_book_black_i00"/>
		<set name="stackable" value="true"/>
		<set name="crystal_type" value="NONE"/>
		<set name="sellable" value="false"/>
		<set name="mailable" value="false"/>
	</etcitem>
	<etcitem id="96288" name="Spellbook: Ultimate Defense Lv. 3" add_name="Sealed">
		<set name="icon" value="icon.etc_magic_book_black_i00"/>
		<set name="stackable" value="true"/>
		<set name="crystal_type" value="NONE"/>
		<set name="tradeable" value="false"/>
		<set name="dropable" value="false"/>
		<set name="privatestoreable" value="false"/>
		<set name="sellable" value="false"/>
		<set name="clan_warehouseable" value="false"/>
		<set name="mailable" value="false"/>
	</etcitem>
	<etcitem id="96289" name="Spellbook: Phoenix Shield">
		<set name="icon" value="icon.etc_magic_book_black_i00"/>
		<set name="stackable" value="true"/>
		<set name="crystal_type" value="NONE"/>
		<set name="sellable" value="false"/>
		<set name="mailable" value="false"/>
	</etcitem>
	<etcitem id="96290" name="Spellbook: Phoenix Shield" add_name="Sealed">
		<set name="icon" value="icon.etc_magic_book_black_i00"/>
		<set name="stackable" value="true"/>
		<set name="crystal_type" value="NONE"/>
		<set name="tradeable" value="false"/>
		<set name="dropable" value="false"/>
		<set name="privatestoreable" value="false"/>
		<set name="sellable" value="false"/>
		<set name="clan_warehouseable" value="false"/>
		<set name="mailable" value="false"/>
	</etcitem>
	<etcitem id="96291" name="Spellbook: Hell">
		<set name="icon" value="icon.etc_magic_book_black_i00"/>
		<set name="stackable" value="true"/>
		<set name="crystal_type" value="NONE"/>
		<set name="sellable" value="false"/>
		<set name="mailable" value="false"/>
	</etcitem>
	<etcitem id="96292" name="Spellbook: Hell" add_name="Sealed">
		<set name="icon" value="icon.etc_magic_book_black_i00"/>
		<set name="stackable" value="true"/>
		<set name="crystal_type" value="NONE"/>
		<set name="tradeable" value="false"/>
		<set name="dropable" value="false"/>
		<set name="privatestoreable" value="false"/>
		<set name="sellable" value="false"/>
		<set name="clan_warehouseable" value="false"/>
		<set name="mailable" value="false"/>
	</etcitem>
	<etcitem id="96293" name="Spellbook: Shelter">
		<set name="icon" value="icon.etc_magic_book_black_i00"/>
		<set name="stackable" value="true"/>
		<set name="crystal_type" value="NONE"/>
		<set name="sellable" value="false"/>
		<set name="mailable" value="false"/>
	</etcitem>
	<etcitem id="96294" name="Spellbook: Shelter" add_name="Sealed">
		<set name="icon" value="icon.etc_magic_book_black_i00"/>
		<set name="stackable" value="true"/>
		<set name="crystal_type" value="NONE"/>
		<set name="tradeable" value="false"/>
		<set name="dropable" value="false"/>
		<set name="privatestoreable" value="false"/>
		<set name="sellable" value="false"/>
		<set name="clan_warehouseable" value="false"/>
		<set name="mailable" value="false"/>
	</etcitem>
	<etcitem id="96295" name="Spellbook: Condemnation">
		<set name="icon" value="icon.etc_magic_book_black_i00"/>
		<set name="stackable" value="true"/>
		<set name="crystal_type" value="NONE"/>
		<set name="sellable" value="false"/>
		<set name="mailable" value="false"/>
	</etcitem>
	<etcitem id="96296" name="Spellbook: Condemnation" add_name="Sealed">
		<set name="icon" value="icon.etc_magic_book_black_i00"/>
		<set name="stackable" value="true"/>
		<set name="crystal_type" value="NONE"/>
		<set name="tradeable" value="false"/>
		<set name="dropable" value="false"/>
		<set name="privatestoreable" value="false"/>
		<set name="sellable" value="false"/>
		<set name="clan_warehouseable" value="false"/>
		<set name="mailable" value="false"/>
	</etcitem>
	<etcitem id="96297" name="Frost Lord's Weapon Pack" add_name="Sealed">
		<set name="icon" value="icon.bm_dragon_present_5"/>
		<set name="stackable" value="true"/>
		<set name="crystal_type" value="NONE"/>
		<set name="tradeable" value="false"/>
		<set name="dropable" value="false"/>
		<set name="privatestoreable" value="false"/>
		<set name="sellable" value="false"/>
		<set name="clan_warehouseable" value="false"/>
		<set name="mailable" value="false"/>
		<set name="type" value="EXTRACTABLE"/>
		<create_items>
			<create_item id="95725" count="1" chance="0.01"/><!--Frost Lord's Sword--><!--TODO: Check chance-->
			<create_item id="95726" count="1" chance="0.01"/><!--Frost Lord's Two-handed Sword--><!--TODO: Check chance-->
			<create_item id="95727" count="1" chance="0.01"/><!--Frost Lord's Axe--><!--TODO: Check chance-->
			<create_item id="95728" count="1" chance="0.01"/><!--Frost Lord's Dagger--><!--TODO: Check chance-->
			<create_item id="95729" count="1" chance="0.01"/><!--Frost Lord's Spear--><!--TODO: Check chance-->
			<create_item id="95730" count="1" chance="0.01"/><!--Frost Lord's Bow--><!--TODO: Check chance-->
			<create_item id="95731" count="1" chance="0.01"/><!--Frost Lord's Blade Fists--><!--TODO: Check chance-->
			<create_item id="95732" count="1" chance="0.01"/><!--Frost Lord's Magic Blunt Weapon--><!--TODO: Check chance-->
			<create_item id="95733" count="1" chance="0.01"/><!--Frost Lord's Staff--><!--TODO: Check chance-->
			<create_item id="95734" count="1" chance="0.01"/><!--Frost Lord's Ancient Sword--><!--TODO: Check chance-->
			<create_item id="95735" count="1" chance="0.01"/><!--Frost Lord's Rapier--><!--TODO: Check chance-->
			<create_item id="95736" count="1" chance="0.01"/><!--Frost Lord's Pistols--><!--TODO: Check chance-->
			<create_item id="95737" count="1" chance="0.01"/><!--Frost Lord's Dual Swords--><!--TODO: Check chance-->
		</create_items>
	</etcitem>
	<etcitem id="96298" name="Rare Scroll Pack (Time-limited)" add_name="Sealed">
		<set name="icon" value="icon.event_hero_treasure_box_i00"/>
		<set name="stackable" value="true"/>
		<set name="crystal_type" value="NONE"/>
		<set name="tradeable" value="false"/>
		<set name="dropable" value="false"/>
		<set name="privatestoreable" value="false"/>
		<set name="sellable" value="false"/>
		<set name="clan_warehouseable" value="false"/>
		<set name="mailable" value="false"/>
		<set name="type" value="EXTRACTABLE"/>
		<create_items>
			<create_item id="95596" count="1" chance="0.01"/><!--Special Scroll: Enchant Dragon Belt (Time-limited)--><!--TODO: Check chance-->
			<create_item id="95597" count="1" chance="0.01"/><!--Special Scroll: Enchant Cloak of Protection (Time-limited)--><!--TODO: Check chance-->
			<create_item id="95598" count="1" chance="0.01"/><!--Special Scroll: Enchant Circlet of Hero (Time-limited)--><!--TODO: Check chance-->
		</create_items>
	</etcitem>
	<etcitem id="96299" name="Recipe: Death Knight's Flame Sword (20%)">
		<set name="icon" value="icon.etc_recipe_black_i00"/>
		<set name="weight" value="30"/>
		<set name="stackable" value="true"/>
		<set name="crystal_type" value="NONE"/>
		<set name="price" value="200000000"/>
		<set name="mailable" value="false"/>
	</etcitem>
</list>